sagemaker_utils/__init__.py
sagemaker_utils/_version.py
sagemaker_utils/render_json.py
sagemaker_utils/utils.py
sagemaker_utils-0.3.6.dist-info/LICENSE
sagemaker_utils-0.3.6.dist-info/METADATA
sagemaker_utils-0.3.6.dist-info/WHEEL
sagemaker_utils-0.3.6.dist-info/top_level.txt
sagemaker_utils-0.3.6.dist-info/RECORD
