Metadata-Version: 2.1
Name: sagemaker-utils
Version: 0.3.6
Summary: Helper functions to work with SageMaker
Author: Edzon Sanchez
Author-email: edzons@amazon.com
License: UNKNOWN
Platform: UNKNOWN
Classifier: Programming Language :: Python :: 3
Classifier: License :: OSI Approved :: MIT License
Classifier: Operating System :: OS Independent
Requires-Python: >=3.6
License-File: LICENSE
Requires-Dist: boto3
Requires-Dist: sagemaker
Requires-Dist: tqdm
Requires-Dist: yaspin
Requires-Dist: pyarrow
